{
  "name": "Дачик CO2 EFEKTA (SensAir S8)",
  "manufacturer": "EfektaLab",
  "model": "EFEKTA_Pixel_Open_Air_II",
  "manufacturerId": "EfektaLab for you",
  "modelId": "EFEKTA_Pixel_Open_Air_II",
  "catalogId": -1,
  "status": "Test",
  "init": [
    {
      "zcl": [
	    {
          "endpoint": 1,
          "cluster": "040D_CarbonDioxide",
          "attribute": "0444_Custom",
          "zclDataType": "UNSIGNED_16_BIT_INTEGER"
        },
        {
          "endpoint": 1,
          "cluster": "040D_CarbonDioxide",
          "attribute": "0402_Custom",
          "zclDataType": "BOOLEAN"
        },
		{
          "endpoint": 1,
          "cluster": "040D_CarbonDioxide",
          "attribute": "0445_Custom",
          "zclDataType": "UNSIGNED_8_BIT_INTEGER"
        },
		{
          "endpoint": 1,
          "cluster": "040D_CarbonDioxide",
          "attribute": "0211_Custom",
          "zclDataType": "BOOLEAN"
        },
		{
          "endpoint": 1,
          "cluster": "040D_CarbonDioxide",
          "attribute": "0401_Custom",
          "zclDataType": "BOOLEAN"
        },
		{
          "endpoint": 1,
          "cluster": "040D_CarbonDioxide",
          "attribute": "0405_Custom",
          "zclDataType": "UNSIGNED_8_BIT_INTEGER"
        },
		{
          "endpoint": 1,
          "cluster": "040D_CarbonDioxide",
          "attribute": "0406_Custom",
          "zclDataType": "UNSIGNED_8_BIT_INTEGER"
        },
		{
          "endpoint": 1,
          "cluster": "040D_CarbonDioxide",
          "attribute": "0220_Custom",
          "zclDataType": "BOOLEAN"
        },
		{
          "endpoint": 1,
          "cluster": "040D_CarbonDioxide",
          "attribute": "0225_Custom",
          "zclDataType": "BOOLEAN"
        },
		{
          "endpoint": 1,
          "cluster": "040D_CarbonDioxide",
          "attribute": "0222_Custom",
          "zclDataType": "UNSIGNED_16_BIT_INTEGER"
        },
		{
          "endpoint": 1,
          "cluster": "040D_CarbonDioxide",
          "attribute": "0221_Custom",
          "zclDataType": "UNSIGNED_16_BIT_INTEGER"
        },
		{
          "endpoint": 2,
          "cluster": "0402_TemperatureMeasurement",
          "attribute": "0210_Custom",
          "zclDataType": "SIGNED_16_BIT_INTEGER"
        },
		{
          "endpoint": 2,
          "cluster": "0405_RelativeHumidityMeasurement",
          "attribute": "0210_Custom",
          "zclDataType": "SIGNED_16_BIT_INTEGER"
        }
      ]
    },
	{
      "link": {
        "endpoint": 1,
        "cluster": "040D_CarbonDioxide",
		"attribute": [
		  "0000_MeasuredValue"
        ]
      },
      "bind": true,
      "report": {
        "min": 15,
        "max": 3600,
        "change": 0.000001
	  }
    },
    {
      "link": {
        "endpoint": 1,
        "cluster": "0003_Identify",
        "attribute": "0000_IdentifyTime"
      },
      "bind": false,
	  "report": false
    },     
    {
      "link": {
        "endpoint": 1,
        "cluster": "000A_Time",
        "attribute": "0007_LocalTime"
      },
      "bind": false,
	  "report": false
    }, 	
	{
      "link": {
        "endpoint": 2,
        "cluster": "0402_TemperatureMeasurement",
        "attribute": "0000_MeasuredValue"
      },
      "bind": true,
      "report": {
        "min": 15,
        "max": 3600,
        "change": 10
	  }
    },
    {
      "link": {
        "endpoint": 2,
        "cluster": "0405_RelativeHumidityMeasurement",
        "attribute": "0000_MeasuredValue"
      },
      "bind": true,
      "report": {
        "min": 15,
        "max": 3600,
        "change": 10
	  }
    }
  ],
  "options": [
    {
      "link": {
        "endpoint": 1,
        "cluster": "040D_CarbonDioxide",
        "attribute": "0445_Custom"
      },
      "name": "Количество ошибое чтения сенсора CO2",
      "type": "Integer",
      "write": false,
      "input": "status",
      "value": 0
    },
	{
      "link": {
        "endpoint": 1,
        "cluster": "040D_CarbonDioxide",
        "attribute": "0402_Custom"
		},
      "name": "Включение автокалибровки датчика CO2",
	  "description": "Встроенный функционал от производителя сенсора, подстройка 1 раз в 7 дней.",
      "type": "Boolean",
      "init": true,
      "value": true
    },
    {
      "link": {
        "endpoint": 1,
        "cluster": "040D_CarbonDioxide",
        "attribute": "0445_Custom",
		"read": false
		},
      "name": "Коррекция контрастности lcd дисплея",
	  "description": "Работает на некоторых моделях дисплеев, чаще контрастностиь дисплеев уже откалибрована.",
      "type": "Integer",
      "init": true,
      "value": 14,
      "minValue": 0,
      "maxValue": 40
    },
    {
      "link": {
        "endpoint": 1,
        "cluster": "040D_CarbonDioxide",
        "attribute": "0211_Custom",
		"read": false
		},
      "name": "RGB подсветка дисплея",
      "type": "Boolean",
      "init": true,
      "value": true
    },
    {
      "link": {
        "endpoint": 1,
        "cluster": "040D_CarbonDioxide",
        "attribute": "0401_Custom",
		"read": false
		},
      "name": "Отключение RGB подсветки дисплея в ночном режиме",
	  "description": "Работает по заданным временным порогам в свойствах активация и деактивация ночнорго режима.",
      "type": "Boolean",
      "init": true,
      "value": false
    },
    {
      "link": {
        "endpoint": 1,
        "cluster": "040D_CarbonDioxide",
        "attribute": "0405_Custom",
		"read": false
		},
      "name": "Время активации ночного режима",
	  "unit": "час",
      "type": "Integer",
      "init": true,
      "value": 22,
      "minValue": 0,
      "maxValue": 23
    },
    {
      "link": {
        "endpoint": 1,
        "cluster": "040D_CarbonDioxide",
        "attribute": "0406_Custom",
		"read": false
		},
      "name": "Время деактивации ночного режима",
	  "unit": "час",
      "type": "Integer",
      "init": true,
      "value": 6,
      "minValue": 0,
      "maxValue": 23
    },
    {
      "link": {
        "endpoint": 2,
        "cluster": "0402_TemperatureMeasurement",
        "attribute": "0210_Custom",
		"read": false
      },
      "name": "Корректировка температуры",
	  "description": "Единица равна корректировке в 0.1°C.",
	  "unit": "°C",
      "type": "Integer",
      "init": true,
      "value": 1,
      "minValue": -50,
      "maxValue": 50
    },
    {
      "link": {
        "endpoint": 2,
        "cluster": "0405_RelativeHumidityMeasurement",
        "attribute": "0210_Custom",
		"read": false
      },
      "name": "Корректировка влажности",
	  "unit": "%",
      "type": "Integer",
      "init": true,
      "value": 1,
      "minValue": -50,
      "maxValue": 50
    },
    {
      "link": {
        "endpoint": 1,
        "cluster": "040D_CarbonDioxide",
        "attribute": "0220_Custom",
		"read": false
		},
      "name": "Газостат СО2",
	  "description": "Активация режима управления внешнего исполнительного устройства, должна быть сделана привязка (bind).",
      "type": "Boolean",
      "init": true,
      "value": false
    },
    {
      "link": {
        "endpoint": 1,
        "cluster": "040D_CarbonDioxide",
        "attribute": "0225_Custom",
		"read": false
		},
      "name": "Газостат СО2, Инвертирование",
	  "description": "Инвертирование логики работы, ...включить, если выше верхнего уровня / ...выключить, если выше верхнего уровня.",
      "type": "Boolean",
      "init": true,
      "value": false
    },
    {
      "link": {
        "endpoint": 1,
        "cluster": "040D_CarbonDioxide",
        "attribute": "0221_Custom",
		"read": false
		},
      "name": "Газостат СО2, верхняя граница",
	  "unit": "ppm",
      "type": "Integer",
      "init": true,
      "value": 2000,
      "minValue": 400,
      "maxValue": 2000
    },
    {
      "link": {
        "endpoint": 1,
        "cluster": "040D_CarbonDioxide",
        "attribute": "0222_Custom",
		"read": false
		},
      "name": "Газостат СО2, нижняя граница",
	  "unit": "ppm",
      "type": "Integer",
      "init": true,
      "value": 400,
      "minValue": 400,
      "maxValue": 2000
    },
    {
      "link": {
        "endpoint": 1,
        "cluster": "0006_OnOff",
        "output": true
      },
      "name": "Прямая работа вкл/выкл",
      "description": "Прямое управление исполнительным устройством (реле, розетки, выключатели).",
      "type": "String",
      "bind": true
    }
  ],
  "services": [
    {
      "type": "CarbonDioxideSensor",
      "logics": [
        {
          "type": "CarbonDioxideDetectedFromCarbonDioxideLevel"
        }
      ],
      "characteristics": [
        {
          "type": "CarbonDioxideLevel",
          "link": [
            {
              "endpoint": 1,
              "cluster": "040D_CarbonDioxide",
              "attribute": "0000_MeasuredValue"
            }
          ]
        }
      ]
    },
    {
      "type": "TemperatureSensor",
      "characteristics": [
        {
          "type": "CurrentTemperature",
          "link": {
            "endpoint": 2,
            "cluster": "0402_TemperatureMeasurement",
            "attribute": "0000_MeasuredValue"
          }
        }
      ]
    },
    {
      "type": "HumiditySensor",
      "characteristics": [
        {
          "type": "CurrentRelativeHumidity",
          "link": {
            "endpoint": 2,
            "cluster": "0405_RelativeHumidityMeasurement",
            "attribute": "0000_MeasuredValue"
          }
        }
      ]
    }
  ]
}